{"city":"連江縣","district":"東引鄉","category":"toilets","updatedAt":"2026-06-12T07:40:23.325Z","rev":1,"count":45,"items":[{"id":2303381770,"name":"羅漢坪","lat":26.3829519,"lng":120.4744081,"address":null,"hasBabyChanging":false,"hasAccessible":false,"source":"OpenStreetMap","updatedAt":"2026-06-12T07:40:23.325Z","facilityType":"attraction","facilityLabel":"🏞️ 景點","changingTable":false,"wheelchair":false,"needsAddr":false},{"id":2303381771,"name":"國之北疆","lat":26.3830744,"lng":120.4760873,"address":null,"hasBabyChanging":false,"hasAccessible":false,"source":"OpenStreetMap","updatedAt":"2026-06-12T07:40:23.325Z","facilityType":"attraction","facilityLabel":"🏞️ 景點","changingTable":false,"wheelchair":false,"needsAddr":false},{"id":2303382607,"name":"一線天","lat":26.3658917,"lng":120.5051395,"address":null,"hasBabyChanging":false,"hasAccessible":false,"source":"OpenStreetMap","updatedAt":"2026-06-12T07:40:23.325Z","facilityType":"attraction","facilityLabel":"🏞️ 景點","changingTable":false,"wheelchair":false,"needsAddr":false},{"id":2303382610,"name":"燕秀潮音","lat":26.3583337,"lng":120.4894963,"address":null,"hasBabyChanging":false,"hasAccessible":false,"source":"OpenStreetMap","updatedAt":"2026-06-12T07:40:23.325Z","facilityType":"attraction","facilityLabel":"🏞️ 景點","changingTable":false,"wheelchair":false,"needsAddr":false},{"id":2654116997,"name":"中柱島","lat":26.3699982,"lng":120.4837122,"address":null,"hasBabyChanging":false,"hasAccessible":false,"source":"OpenStreetMap","updatedAt":"2026-06-12T07:40:23.325Z","facilityType":"attraction","facilityLabel":"🏞️ 景點","changingTable":false,"wheelchair":false,"needsAddr":false},{"id":4721922736,"name":"烈女義坑","lat":26.3686441,"lng":120.507637,"address":null,"hasBabyChanging":false,"hasAccessible":false,"source":"OpenStreetMap","updatedAt":"2026-06-12T07:40:23.325Z","facilityType":"attraction","facilityLabel":"🏞️ 景點","changingTable":false,"wheelchair":false,"needsAddr":false},{"id":4741522221,"name":"33據點","lat":26.3722011,"lng":120.4698433,"address":null,"hasBabyChanging":false,"hasAccessible":false,"source":"OpenStreetMap","updatedAt":"2026-06-12T07:40:23.325Z","facilityType":"attraction","facilityLabel":"🏞️ 景點","changingTable":false,"wheelchair":false,"needsAddr":false},{"id":5146218653,"name":"梅台","lat":26.3681039,"lng":120.4855037,"address":null,"hasBabyChanging":false,"hasAccessible":false,"source":"OpenStreetMap","updatedAt":"2026-06-12T07:40:23.325Z","facilityType":"attraction","facilityLabel":"🏞️ 景點","changingTable":false,"wheelchair":false,"needsAddr":false},{"id":5146233084,"name":"霧砲","lat":26.3652922,"lng":120.5105822,"address":null,"hasBabyChanging":false,"hasAccessible":false,"source":"OpenStreetMap","updatedAt":"2026-06-12T07:40:23.325Z","facilityType":"attraction","facilityLabel":"🏞️ 景點","changingTable":false,"wheelchair":false,"needsAddr":false},{"id":5146902580,"name":"北海坑道","lat":26.3587895,"lng":120.4853437,"address":null,"hasBabyChanging":false,"hasAccessible":false,"source":"OpenStreetMap","updatedAt":"2026-06-12T07:40:23.325Z","facilityType":"attraction","facilityLabel":"🏞️ 景點","changingTable":false,"wheelchair":false,"needsAddr":false},{"id":5146902581,"name":"鱷魚島","lat":26.3761665,"lng":120.4721393,"address":null,"hasBabyChanging":false,"hasAccessible":false,"source":"OpenStreetMap","updatedAt":"2026-06-12T07:40:23.325Z","facilityType":"attraction","facilityLabel":"🏞️ 景點","changingTable":false,"wheelchair":false,"needsAddr":false},{"id":5146902582,"name":"和尚看經","lat":26.3691311,"lng":120.4782354,"address":null,"hasBabyChanging":false,"hasAccessible":false,"source":"OpenStreetMap","updatedAt":"2026-06-12T07:40:23.325Z","facilityType":"attraction","facilityLabel":"🏞️ 景點","changingTable":false,"wheelchair":false,"needsAddr":false},{"id":7492657485,"name":"海龍現闕","lat":26.3709246,"lng":120.4880253,"address":null,"hasBabyChanging":false,"hasAccessible":false,"source":"OpenStreetMap","updatedAt":"2026-06-12T07:40:23.325Z","facilityType":"attraction","facilityLabel":"🏞️ 景點","changingTable":false,"wheelchair":false,"needsAddr":false},{"id":8096931891,"name":"公共廁所","lat":26.3659346,"lng":120.5099187,"address":null,"hasBabyChanging":false,"hasAccessible":false,"source":"OpenStreetMap","updatedAt":"2026-06-12T07:40:23.325Z","facilityType":"toilet","facilityLabel":null,"changingTable":false,"wheelchair":false,"fee":"no","needsAddr":true},{"id":10573928910,"name":"公共廁所","lat":26.3727245,"lng":120.4706129,"address":null,"hasBabyChanging":false,"hasAccessible":false,"source":"OpenStreetMap","updatedAt":"2026-06-12T07:40:23.325Z","facilityType":"toilet","facilityLabel":null,"changingTable":false,"wheelchair":false,"needsAddr":true},{"id":10574153709,"name":"公共廁所","lat":26.3654207,"lng":120.4865523,"address":null,"hasBabyChanging":false,"hasAccessible":false,"source":"OpenStreetMap","updatedAt":"2026-06-12T07:40:23.325Z","facilityType":"toilet","facilityLabel":null,"changingTable":false,"wheelchair":false,"needsAddr":true},{"id":10574172609,"name":"公共廁所","lat":26.3599367,"lng":120.4838456,"address":null,"hasBabyChanging":false,"hasAccessible":false,"source":"OpenStreetMap","updatedAt":"2026-06-12T07:40:23.325Z","facilityType":"toilet","facilityLabel":null,"changingTable":false,"wheelchair":false,"needsAddr":true},{"id":10716216905,"name":"鐵騎堡","lat":26.3680998,"lng":120.4861789,"address":null,"hasBabyChanging":false,"hasAccessible":false,"source":"OpenStreetMap","updatedAt":"2026-06-12T07:40:23.325Z","facilityType":"attraction","facilityLabel":"🏞️ 景點","changingTable":false,"wheelchair":false,"needsAddr":false},{"id":10718111105,"name":"最靠北的公廁","lat":26.3811884,"lng":120.4769165,"address":null,"hasBabyChanging":false,"hasAccessible":false,"source":"OpenStreetMap","updatedAt":"2026-06-12T07:40:23.325Z","facilityType":"toilet","facilityLabel":null,"changingTable":false,"wheelchair":false,"needsAddr":false},{"id":10718248806,"name":"祥記商店 (東引中路故事館)","lat":26.36709,"lng":120.4872224,"address":null,"hasBabyChanging":false,"hasAccessible":false,"source":"OpenStreetMap","updatedAt":"2026-06-12T07:40:23.325Z","facilityType":"museum","facilityLabel":"🖼️ 博物館","changingTable":false,"wheelchair":false,"needsAddr":false},{"id":10724674605,"name":"老鼠沙石林","lat":26.3582834,"lng":120.4892613,"address":null,"hasBabyChanging":false,"hasAccessible":false,"source":"OpenStreetMap","updatedAt":"2026-06-12T07:40:23.325Z","facilityType":"attraction","facilityLabel":"🏞️ 景點","changingTable":false,"wheelchair":false,"needsAddr":false},{"id":10821203835,"name":"靜伏鱷魚","lat":26.3756886,"lng":120.4779685,"address":null,"hasBabyChanging":false,"hasAccessible":false,"source":"OpenStreetMap","updatedAt":"2026-06-12T07:40:23.325Z","facilityType":"attraction","facilityLabel":"🏞️ 景點","changingTable":false,"wheelchair":false,"needsAddr":false},{"id":369067215,"name":"中柱漁港","lat":26.3641582,"lng":120.4849587,"address":null,"hasBabyChanging":false,"hasAccessible":false,"source":"OpenStreetMap","updatedAt":"2026-06-12T07:40:23.325Z","facilityType":"harbour","facilityLabel":"⚓ 漁港","changingTable":false,"wheelchair":false,"needsAddr":false},{"id":431591104,"name":"東引鄉公所","lat":26.3674929,"lng":120.4898879,"address":null,"hasBabyChanging":false,"hasAccessible":false,"source":"OpenStreetMap","updatedAt":"2026-06-12T07:40:23.325Z","facilityType":"government","facilityLabel":"🏛 公務機關","changingTable":false,"wheelchair":false,"needsAddr":false},{"id":431591548,"name":"東引酒廠","lat":26.3639093,"lng":120.490246,"address":"212連江縣東引鄉樂華村161號","hasBabyChanging":false,"hasAccessible":false,"source":"OpenStreetMap","updatedAt":"2026-06-12T07:40:23.325Z","facilityType":"winery","facilityLabel":"🍶 酒廠","changingTable":false,"wheelchair":false,"needsAddr":false},{"id":431591550,"name":"東引鄉衛生所","lat":26.3672744,"lng":120.49086,"address":"連江縣東引鄉中柳村123號","hasBabyChanging":false,"hasAccessible":false,"source":"OpenStreetMap","updatedAt":"2026-06-12T07:40:23.325Z","facilityType":"clinic","facilityLabel":"🩺 診所","changingTable":false,"wheelchair":false,"needsAddr":false},{"id":431591554,"name":"東引加油站","lat":26.3690723,"lng":120.4884609,"address":null,"hasBabyChanging":false,"hasAccessible":false,"source":"OpenStreetMap","updatedAt":"2026-06-12T07:40:23.325Z","facilityType":"fuel","facilityLabel":"⛽ 加油站","changingTable":false,"wheelchair":false,"needsAddr":false},{"id":529638249,"name":"東引醫院","lat":26.3741328,"lng":120.4969165,"address":null,"hasBabyChanging":false,"hasAccessible":false,"source":"OpenStreetMap","updatedAt":"2026-06-12T07:40:23.325Z","facilityType":"hospital","facilityLabel":"🏥 醫院","changingTable":false,"wheelchair":false,"needsAddr":false},{"id":529693205,"name":"公共廁所","lat":26.3680747,"lng":120.488183,"address":null,"hasBabyChanging":false,"hasAccessible":false,"source":"OpenStreetMap","updatedAt":"2026-06-12T07:40:23.325Z","facilityType":"toilet","facilityLabel":null,"changingTable":false,"wheelchair":false,"needsAddr":true},{"id":529693213,"name":"圖書館","lat":26.3676823,"lng":120.4887516,"address":null,"hasBabyChanging":false,"hasAccessible":false,"source":"OpenStreetMap","updatedAt":"2026-06-12T07:40:23.325Z","facilityType":"library","facilityLabel":"📚 圖書館","changingTable":false,"wheelchair":false,"needsAddr":false},{"id":529693218,"name":"東引警察所","lat":26.3677038,"lng":120.4897251,"address":"連江縣東引鄉中柳村121之1號","hasBabyChanging":false,"hasAccessible":false,"source":"OpenStreetMap","updatedAt":"2026-06-12T07:40:23.325Z","facilityType":"police","facilityLabel":"🚔 派出所","changingTable":false,"wheelchair":false,"needsAddr":false},{"id":529693223,"name":"東引戶政事務所","lat":26.3672807,"lng":120.4901351,"address":null,"hasBabyChanging":false,"hasAccessible":false,"source":"OpenStreetMap","updatedAt":"2026-06-12T07:40:23.325Z","facilityType":"government","facilityLabel":"🏛 公務機關","changingTable":false,"wheelchair":false,"needsAddr":false},{"id":529696791,"name":"公共廁所","lat":26.3671442,"lng":120.5078759,"address":null,"hasBabyChanging":false,"hasAccessible":false,"source":"OpenStreetMap","updatedAt":"2026-06-12T07:40:23.325Z","facilityType":"toilet","facilityLabel":null,"changingTable":false,"wheelchair":false,"needsAddr":true},{"id":529704454,"name":"志清圖書館","lat":26.3640983,"lng":120.4923863,"address":null,"hasBabyChanging":false,"hasAccessible":false,"source":"OpenStreetMap","updatedAt":"2026-06-12T07:40:23.325Z","facilityType":"library","facilityLabel":"📚 圖書館","changingTable":false,"wheelchair":false,"needsAddr":false},{"id":529813026,"name":"中柱安檢所","lat":26.363847,"lng":120.4859632,"address":"連江縣東引鄉樂華村160之3號","hasBabyChanging":false,"hasAccessible":false,"source":"OpenStreetMap","updatedAt":"2026-06-12T07:40:23.325Z","facilityType":"police","facilityLabel":"🚔 派出所","changingTable":false,"wheelchair":false,"needsAddr":false},{"id":529813034,"name":"白馬尊王廟","lat":26.3656626,"lng":120.4865823,"address":null,"hasBabyChanging":false,"hasAccessible":false,"source":"OpenStreetMap","updatedAt":"2026-06-12T07:40:23.325Z","facilityType":"temple","facilityLabel":"🛕 廟宇","changingTable":false,"wheelchair":false,"needsAddr":false},{"id":529813036,"name":"東引禮拜堂","lat":26.3658528,"lng":120.4873908,"address":null,"hasBabyChanging":false,"hasAccessible":false,"source":"OpenStreetMap","updatedAt":"2026-06-12T07:40:23.325Z","facilityType":"temple","facilityLabel":"🛕 廟宇","changingTable":false,"wheelchair":false,"needsAddr":false},{"id":529813039,"name":"東引中柳天后宮","lat":26.367037,"lng":120.4867457,"address":"連江縣東引鄉樂華村52號","hasBabyChanging":false,"hasAccessible":false,"source":"OpenStreetMap","updatedAt":"2026-06-12T07:40:23.325Z","facilityType":"temple","facilityLabel":"🛕 廟宇","changingTable":false,"wheelchair":false,"needsAddr":false},{"id":529816024,"name":"安寧廟","lat":26.3687361,"lng":120.4857511,"address":null,"hasBabyChanging":false,"hasAccessible":false,"source":"OpenStreetMap","updatedAt":"2026-06-12T07:40:23.325Z","facilityType":"temple","facilityLabel":"🛕 廟宇","changingTable":false,"wheelchair":false,"needsAddr":false},{"id":529816031,"name":"關帝廟","lat":26.3681804,"lng":120.4859796,"address":null,"hasBabyChanging":false,"hasAccessible":false,"source":"OpenStreetMap","updatedAt":"2026-06-12T07:40:23.325Z","facilityType":"temple","facilityLabel":"🛕 廟宇","changingTable":false,"wheelchair":false,"needsAddr":false},{"id":529897511,"name":"煜光堂(西引文康中心)","lat":26.3770531,"lng":120.4795642,"address":null,"hasBabyChanging":false,"hasAccessible":false,"source":"OpenStreetMap","updatedAt":"2026-06-12T07:40:23.325Z","facilityType":"community","facilityLabel":"🏘️ 活動中心","changingTable":false,"wheelchair":false,"needsAddr":false},{"id":529897514,"name":"忠義廟","lat":26.3796821,"lng":120.4768376,"address":"連江縣東引鄉中清路136號","hasBabyChanging":false,"hasAccessible":false,"source":"OpenStreetMap","updatedAt":"2026-06-12T07:40:23.325Z","facilityType":"temple","facilityLabel":"🛕 廟宇","changingTable":false,"wheelchair":false,"needsAddr":false},{"id":529910262,"name":"廟宇","lat":26.3678651,"lng":120.486997,"address":null,"hasBabyChanging":false,"hasAccessible":false,"source":"OpenStreetMap","updatedAt":"2026-06-12T07:40:23.325Z","facilityType":"temple","facilityLabel":"🛕 廟宇","changingTable":false,"wheelchair":false,"needsAddr":true},{"id":529910269,"name":"廟宇","lat":26.3675578,"lng":120.4859505,"address":null,"hasBabyChanging":false,"hasAccessible":false,"source":"OpenStreetMap","updatedAt":"2026-06-12T07:40:23.325Z","facilityType":"temple","facilityLabel":"🛕 廟宇","changingTable":false,"wheelchair":false,"needsAddr":true},{"id":1163544728,"name":"公共廁所","lat":26.3796217,"lng":120.477114,"address":null,"hasBabyChanging":false,"hasAccessible":false,"source":"OpenStreetMap","updatedAt":"2026-06-12T07:40:23.325Z","facilityType":"toilet","facilityLabel":null,"changingTable":false,"wheelchair":false,"needsAddr":true}]}