{"city":"宜蘭縣","district":"員山鄉","category":"toilets","updatedAt":"2026-06-12T07:40:23.325Z","rev":1,"count":93,"items":[{"id":204496928,"name":"福山植物園管制站","lat":24.7521201,"lng":121.6127899,"address":null,"hasBabyChanging":false,"hasAccessible":false,"source":"OpenStreetMap","updatedAt":"2026-06-12T07:40:23.325Z","facilityType":"botanical","facilityLabel":"🌿 植物園","changingTable":false,"wheelchair":false,"needsAddr":false},{"id":2144962517,"name":"公共廁所","lat":24.7521395,"lng":121.6128493,"address":null,"hasBabyChanging":false,"hasAccessible":false,"source":"OpenStreetMap","updatedAt":"2026-06-12T07:40:23.325Z","facilityType":"toilet","facilityLabel":null,"changingTable":false,"wheelchair":false,"needsAddr":true},{"id":2536763457,"name":"內城派出所","lat":24.7150041,"lng":121.6953619,"address":"宜蘭縣員山鄉內成村員山路二段235號","hasBabyChanging":false,"hasAccessible":false,"source":"OpenStreetMap","updatedAt":"2026-06-12T07:40:23.325Z","facilityType":"police","facilityLabel":"🚔 派出所","changingTable":false,"wheelchair":false,"needsAddr":false},{"id":2536764025,"name":"員山分駐所","lat":24.7451785,"lng":121.7267267,"address":"宜蘭縣員山鄉員山村員山路一段205號","hasBabyChanging":false,"hasAccessible":false,"source":"OpenStreetMap","updatedAt":"2026-06-12T07:40:23.325Z","facilityType":"police","facilityLabel":"🚔 派出所","changingTable":false,"wheelchair":false,"needsAddr":false},{"id":2536764277,"name":"大湖派出所","lat":24.7432813,"lng":121.6974297,"address":"宜蘭縣員山鄉逸仙村大安路120號","hasBabyChanging":false,"hasAccessible":false,"source":"OpenStreetMap","updatedAt":"2026-06-12T07:40:23.325Z","facilityType":"police","facilityLabel":"🚔 派出所","changingTable":false,"wheelchair":false,"needsAddr":false},{"id":2536764864,"name":"惠好派出所","lat":24.7292072,"lng":121.7292173,"address":"宜蘭縣員山鄉惠好村尚惠路63號","hasBabyChanging":false,"hasAccessible":false,"source":"OpenStreetMap","updatedAt":"2026-06-12T07:40:23.325Z","facilityType":"police","facilityLabel":"🚔 派出所","changingTable":false,"wheelchair":false,"needsAddr":false},{"id":2536765399,"name":"枕山派出所","lat":24.7589612,"lng":121.7186337,"address":"宜蘭縣員山鄉永和村永同路三段18號","hasBabyChanging":false,"hasAccessible":false,"source":"OpenStreetMap","updatedAt":"2026-06-12T07:40:23.325Z","facilityType":"police","facilityLabel":"🚔 派出所","changingTable":false,"wheelchair":false,"needsAddr":false},{"id":2536765846,"name":"粗坑派出所","lat":24.7084235,"lng":121.6487753,"address":"宜蘭縣員山鄉員山路三段316號","hasBabyChanging":false,"hasAccessible":false,"source":"OpenStreetMap","updatedAt":"2026-06-12T07:40:23.325Z","facilityType":"police","facilityLabel":"🚔 派出所","changingTable":false,"wheelchair":false,"needsAddr":false},{"id":2706753773,"name":"台灣中油 員山站","lat":24.7475367,"lng":121.7311069,"address":null,"hasBabyChanging":false,"hasAccessible":false,"source":"OpenStreetMap","updatedAt":"2026-06-12T07:40:23.325Z","facilityType":"fuel","facilityLabel":"⛽ 加油站","changingTable":false,"wheelchair":false,"needsAddr":false},{"id":2706753774,"name":"台塑石油 太山加油站","lat":24.7482087,"lng":121.731361,"address":null,"hasBabyChanging":false,"hasAccessible":false,"source":"OpenStreetMap","updatedAt":"2026-06-12T07:40:23.325Z","facilityType":"fuel","facilityLabel":"⛽ 加油站","changingTable":false,"wheelchair":false,"needsAddr":false},{"id":2742043494,"name":"台灣中油 同樂站","lat":24.763684,"lng":121.7277209,"address":null,"hasBabyChanging":false,"hasAccessible":false,"source":"OpenStreetMap","updatedAt":"2026-06-12T07:40:23.325Z","facilityType":"fuel","facilityLabel":"⛽ 加油站","changingTable":false,"wheelchair":false,"needsAddr":false},{"id":5108954588,"name":"吉姆老爹啤酒工廠","lat":24.7080653,"lng":121.6836342,"address":null,"hasBabyChanging":false,"hasAccessible":false,"source":"OpenStreetMap","updatedAt":"2026-06-12T07:40:23.325Z","facilityType":"attraction","facilityLabel":"🏞️ 景點","changingTable":false,"wheelchair":false,"needsAddr":false},{"id":5109027722,"name":"7-Eleven 佳怡門市","lat":24.7459763,"lng":121.7272979,"address":"264宜蘭縣員山鄉員山村員山路一段184號","hasBabyChanging":false,"hasAccessible":false,"source":"OpenStreetMap","updatedAt":"2026-06-12T07:40:23.325Z","facilityType":"convenience","facilityLabel":"🏪 超商","changingTable":false,"wheelchair":false,"openingHours":"24/7","needsAddr":false},{"id":5109027769,"name":"蚊煙路(金車酒廠)","lat":24.7137182,"lng":121.6925096,"address":null,"hasBabyChanging":false,"hasAccessible":false,"source":"OpenStreetMap","updatedAt":"2026-06-12T07:40:23.325Z","facilityType":"winery","facilityLabel":"🍶 酒廠","changingTable":false,"wheelchair":false,"needsAddr":false},{"id":5179982690,"name":"金車文藝中心B1F","lat":24.7159142,"lng":121.6926236,"address":null,"hasBabyChanging":false,"hasAccessible":false,"source":"OpenStreetMap","updatedAt":"2026-06-12T07:40:23.325Z","facilityType":"arts","facilityLabel":"🎭 藝文場館","changingTable":false,"wheelchair":false,"needsAddr":false},{"id":5522126359,"name":"萬善祠","lat":24.7488724,"lng":121.7119302,"address":null,"hasBabyChanging":false,"hasAccessible":false,"source":"OpenStreetMap","updatedAt":"2026-06-12T07:40:23.325Z","facilityType":"temple","facilityLabel":"🛕 廟宇","changingTable":false,"wheelchair":false,"needsAddr":false},{"id":5522126360,"name":"聖猴宮","lat":24.7487244,"lng":121.703835,"address":null,"hasBabyChanging":false,"hasAccessible":false,"source":"OpenStreetMap","updatedAt":"2026-06-12T07:40:23.325Z","facilityType":"temple","facilityLabel":"🛕 廟宇","changingTable":false,"wheelchair":false,"needsAddr":false},{"id":5526630321,"name":"大三鬮慈惠寺","lat":24.7389118,"lng":121.7223566,"address":null,"hasBabyChanging":false,"hasAccessible":false,"source":"OpenStreetMap","updatedAt":"2026-06-12T07:40:23.325Z","facilityType":"temple","facilityLabel":"🛕 廟宇","changingTable":false,"wheelchair":false,"needsAddr":false},{"id":5696308635,"name":"稼穡林蔭步道","lat":24.7639071,"lng":121.6730819,"address":null,"hasBabyChanging":false,"hasAccessible":false,"source":"OpenStreetMap","updatedAt":"2026-06-12T07:40:23.325Z","facilityType":"attraction","facilityLabel":"🏞️ 景點","changingTable":false,"wheelchair":false,"needsAddr":false},{"id":5696310831,"name":"公共廁所","lat":24.7608963,"lng":121.6742581,"address":null,"hasBabyChanging":false,"hasAccessible":false,"source":"OpenStreetMap","updatedAt":"2026-06-12T07:40:23.325Z","facilityType":"toilet","facilityLabel":null,"changingTable":false,"wheelchair":false,"needsAddr":true},{"id":5696310832,"name":"帝恩廟","lat":24.7607993,"lng":121.6737965,"address":null,"hasBabyChanging":false,"hasAccessible":false,"source":"OpenStreetMap","updatedAt":"2026-06-12T07:40:23.325Z","facilityType":"temple","facilityLabel":"🛕 廟宇","changingTable":false,"wheelchair":false,"needsAddr":false},{"id":5696325632,"name":"燈篙林道","lat":24.7620172,"lng":121.6749,"address":null,"hasBabyChanging":false,"hasAccessible":false,"source":"OpenStreetMap","updatedAt":"2026-06-12T07:40:23.325Z","facilityType":"attraction","facilityLabel":"🏞️ 景點","changingTable":false,"wheelchair":false,"needsAddr":false},{"id":5696330921,"name":"燈篙林道促進會","lat":24.7655677,"lng":121.6729229,"address":null,"hasBabyChanging":false,"hasAccessible":false,"source":"OpenStreetMap","updatedAt":"2026-06-12T07:40:23.325Z","facilityType":"community","facilityLabel":"🏘️ 活動中心","changingTable":false,"wheelchair":false,"needsAddr":false},{"id":5696332522,"name":"雙月湖","lat":24.7758773,"lng":121.6691925,"address":null,"hasBabyChanging":false,"hasAccessible":false,"source":"OpenStreetMap","updatedAt":"2026-06-12T07:40:23.325Z","facilityType":"attraction","facilityLabel":"🏞️ 景點","changingTable":false,"wheelchair":false,"needsAddr":false},{"id":5696332523,"name":"燈篙石梯","lat":24.7650844,"lng":121.6745254,"address":null,"hasBabyChanging":false,"hasAccessible":false,"source":"OpenStreetMap","updatedAt":"2026-06-12T07:40:23.325Z","facilityType":"attraction","facilityLabel":"🏞️ 景點","changingTable":false,"wheelchair":false,"needsAddr":false},{"id":5696333521,"name":"獨立樟","lat":24.768363,"lng":121.6740865,"address":null,"hasBabyChanging":false,"hasAccessible":false,"source":"OpenStreetMap","updatedAt":"2026-06-12T07:40:23.325Z","facilityType":"attraction","facilityLabel":"🏞️ 景點","changingTable":false,"wheelchair":false,"needsAddr":false},{"id":5696336021,"name":"望林找龜","lat":24.7745496,"lng":121.6731545,"address":null,"hasBabyChanging":false,"hasAccessible":false,"source":"OpenStreetMap","updatedAt":"2026-06-12T07:40:23.325Z","facilityType":"attraction","facilityLabel":"🏞️ 景點","changingTable":false,"wheelchair":false,"needsAddr":false},{"id":5696337921,"name":"崩山湖遠眺","lat":24.7731611,"lng":121.6713604,"address":null,"hasBabyChanging":false,"hasAccessible":false,"source":"OpenStreetMap","updatedAt":"2026-06-12T07:40:23.325Z","facilityType":"attraction","facilityLabel":"🏞️ 景點","changingTable":false,"wheelchair":false,"needsAddr":false},{"id":7764639651,"name":"枕山宜蘭夜景","lat":24.7705871,"lng":121.7220444,"address":null,"hasBabyChanging":false,"hasAccessible":false,"source":"OpenStreetMap","updatedAt":"2026-06-12T07:40:23.325Z","facilityType":"attraction","facilityLabel":"🏞️ 景點","changingTable":false,"wheelchair":false,"needsAddr":false},{"id":8402089891,"name":"員山衛生所","lat":24.7442955,"lng":121.7240463,"address":null,"hasBabyChanging":false,"hasAccessible":false,"source":"OpenStreetMap","updatedAt":"2026-06-12T07:40:23.325Z","facilityType":"clinic","facilityLabel":"🩺 診所","changingTable":false,"wheelchair":false,"needsAddr":false},{"id":9630717884,"name":"萬善堂","lat":24.7145757,"lng":121.6818969,"address":null,"hasBabyChanging":false,"hasAccessible":false,"source":"OpenStreetMap","updatedAt":"2026-06-12T07:40:23.325Z","facilityType":"temple","facilityLabel":"🛕 廟宇","changingTable":false,"wheelchair":false,"needsAddr":false},{"id":10091208810,"name":"員山鄉農會大湖分部","lat":24.7446289,"lng":121.7017546,"address":"宜蘭縣員山鄉大湖路15-57號","hasBabyChanging":false,"hasAccessible":false,"source":"OpenStreetMap","updatedAt":"2026-06-12T07:40:23.325Z","facilityType":"government","facilityLabel":"🏛 公務機關","changingTable":false,"wheelchair":false,"needsAddr":false},{"id":10556870149,"name":"公共廁所","lat":24.7272919,"lng":121.7114063,"address":null,"hasBabyChanging":false,"hasAccessible":false,"source":"OpenStreetMap","updatedAt":"2026-06-12T07:40:23.325Z","facilityType":"toilet","facilityLabel":null,"changingTable":false,"wheelchair":false,"needsAddr":true},{"id":10786631557,"name":"呂氏古厝","lat":24.7420756,"lng":121.6939996,"address":null,"hasBabyChanging":false,"hasAccessible":false,"source":"OpenStreetMap","updatedAt":"2026-06-12T07:40:23.325Z","facilityType":"temple","facilityLabel":"🛕 廟宇","changingTable":false,"wheelchair":false,"needsAddr":false},{"id":10786631558,"name":"大安宮","lat":24.740462,"lng":121.6926559,"address":null,"hasBabyChanging":false,"hasAccessible":false,"source":"OpenStreetMap","updatedAt":"2026-06-12T07:40:23.325Z","facilityType":"temple","facilityLabel":"🛕 廟宇","changingTable":false,"wheelchair":false,"needsAddr":false},{"id":11050134248,"name":"撤退嶺","lat":24.7758483,"lng":121.6086941,"address":null,"hasBabyChanging":false,"hasAccessible":false,"source":"OpenStreetMap","updatedAt":"2026-06-12T07:40:23.325Z","facilityType":"attraction","facilityLabel":"🏞️ 景點","changingTable":false,"wheelchair":false,"needsAddr":false},{"id":11135832952,"name":"保民廟","lat":24.7155968,"lng":121.7198172,"address":null,"hasBabyChanging":false,"hasAccessible":false,"source":"OpenStreetMap","updatedAt":"2026-06-12T07:40:23.325Z","facilityType":"temple","facilityLabel":"🛕 廟宇","changingTable":false,"wheelchair":false,"needsAddr":false},{"id":11342905269,"name":"勞動部勞動力發展署北基宜花金馬分署宜蘭職業訓練場","lat":24.6916565,"lng":121.6321061,"address":"264宜蘭縣員山鄉員山路三段500巷1號","hasBabyChanging":false,"hasAccessible":false,"source":"OpenStreetMap","updatedAt":"2026-06-12T07:40:23.325Z","facilityType":"government","facilityLabel":"🏛 公務機關","changingTable":false,"wheelchair":false,"needsAddr":false},{"id":12135359755,"name":"公共廁所","lat":24.6940506,"lng":121.6337968,"address":null,"hasBabyChanging":false,"hasAccessible":false,"source":"OpenStreetMap","updatedAt":"2026-06-12T07:40:23.325Z","facilityType":"toilet","facilityLabel":null,"changingTable":false,"wheelchair":false,"needsAddr":true},{"id":12135359759,"name":"豐盛愛玉","lat":24.6939665,"lng":121.6340219,"address":null,"hasBabyChanging":false,"hasAccessible":false,"source":"OpenStreetMap","updatedAt":"2026-06-12T07:40:23.325Z","facilityType":"attraction","facilityLabel":"🏞️ 景點","changingTable":false,"wheelchair":false,"needsAddr":false},{"id":12728572316,"name":"景點","lat":24.7142302,"lng":121.681068,"address":null,"hasBabyChanging":false,"hasAccessible":false,"source":"OpenStreetMap","updatedAt":"2026-06-12T07:40:23.325Z","facilityType":"attraction","facilityLabel":"🏞️ 景點","changingTable":false,"wheelchair":false,"needsAddr":true},{"id":12840991367,"name":"太平保宮殿","lat":24.7134618,"lng":121.6645805,"address":null,"hasBabyChanging":false,"hasAccessible":false,"source":"OpenStreetMap","updatedAt":"2026-06-12T07:40:23.325Z","facilityType":"temple","facilityLabel":"🛕 廟宇","changingTable":false,"wheelchair":false,"needsAddr":false},{"id":12841027109,"name":"玉雲宮","lat":24.7093519,"lng":121.6619854,"address":null,"hasBabyChanging":false,"hasAccessible":false,"source":"OpenStreetMap","updatedAt":"2026-06-12T07:40:23.325Z","facilityType":"temple","facilityLabel":"🛕 廟宇","changingTable":false,"wheelchair":false,"needsAddr":false},{"id":12860111149,"name":"結福廟","lat":24.7580006,"lng":121.7271826,"address":null,"hasBabyChanging":false,"hasAccessible":false,"source":"OpenStreetMap","updatedAt":"2026-06-12T07:40:23.325Z","facilityType":"temple","facilityLabel":"🛕 廟宇","changingTable":false,"wheelchair":false,"needsAddr":false},{"id":13431347549,"name":"景點","lat":24.745192,"lng":121.7200368,"address":null,"hasBabyChanging":false,"hasAccessible":false,"source":"OpenStreetMap","updatedAt":"2026-06-12T07:40:23.325Z","facilityType":"attraction","facilityLabel":"🏞️ 景點","changingTable":false,"wheelchair":false,"needsAddr":true},{"id":237469163,"name":"三官宮","lat":24.7215284,"lng":121.7162417,"address":null,"hasBabyChanging":false,"hasAccessible":false,"source":"OpenStreetMap","updatedAt":"2026-06-12T07:40:23.325Z","facilityType":"temple","facilityLabel":"🛕 廟宇","changingTable":false,"wheelchair":false,"needsAddr":false},{"id":237793959,"name":"廟宇","lat":24.7178189,"lng":121.7106309,"address":null,"hasBabyChanging":false,"hasAccessible":false,"source":"OpenStreetMap","updatedAt":"2026-06-12T07:40:23.325Z","facilityType":"temple","facilityLabel":"🛕 廟宇","changingTable":false,"wheelchair":false,"needsAddr":true},{"id":238274092,"name":"土地公廟","lat":24.7522556,"lng":121.6325164,"address":null,"hasBabyChanging":false,"hasAccessible":false,"source":"OpenStreetMap","updatedAt":"2026-06-12T07:40:23.325Z","facilityType":"temple","facilityLabel":"🛕 廟宇","changingTable":false,"wheelchair":false,"needsAddr":false},{"id":340266525,"name":"金車威士忌酒廠","lat":24.7142864,"lng":121.6893055,"address":"宜蘭縣員山鄉員山路二段326號","hasBabyChanging":false,"hasAccessible":false,"source":"OpenStreetMap","updatedAt":"2026-06-12T07:40:23.325Z","facilityType":"winery","facilityLabel":"🍶 酒廠","changingTable":false,"wheelchair":false,"needsAddr":false},{"id":407493467,"name":"福山植物園","lat":24.7601304,"lng":121.5882898,"address":null,"hasBabyChanging":false,"hasAccessible":false,"source":"OpenStreetMap","updatedAt":"2026-06-12T07:40:23.325Z","facilityType":"botanical","facilityLabel":"🌿 植物園","changingTable":false,"wheelchair":false,"needsAddr":false},{"id":471477701,"name":"蓁巷三賢廟","lat":24.717042,"lng":121.7020351,"address":null,"hasBabyChanging":false,"hasAccessible":false,"source":"OpenStreetMap","updatedAt":"2026-06-12T07:40:23.325Z","facilityType":"temple","facilityLabel":"🛕 廟宇","changingTable":false,"wheelchair":false,"needsAddr":false},{"id":479639260,"name":"聖壇宮","lat":24.7180324,"lng":121.7257812,"address":null,"hasBabyChanging":false,"hasAccessible":false,"source":"OpenStreetMap","updatedAt":"2026-06-12T07:40:23.325Z","facilityType":"temple","facilityLabel":"🛕 廟宇","changingTable":false,"wheelchair":false,"needsAddr":false},{"id":482141699,"name":"廣成宮","lat":24.7212519,"lng":121.7233131,"address":null,"hasBabyChanging":false,"hasAccessible":false,"source":"OpenStreetMap","updatedAt":"2026-06-12T07:40:23.325Z","facilityType":"temple","facilityLabel":"🛕 廟宇","changingTable":false,"wheelchair":false,"needsAddr":false},{"id":534023691,"name":"香草菲菲芳香植物博物館","lat":24.7147612,"lng":121.6823289,"address":null,"hasBabyChanging":false,"hasAccessible":false,"source":"OpenStreetMap","updatedAt":"2026-06-12T07:40:23.325Z","facilityType":"attraction","facilityLabel":"🏞️ 景點","changingTable":false,"wheelchair":false,"needsAddr":false},{"id":534023692,"name":"公共廁所","lat":24.7147223,"lng":121.6827725,"address":null,"hasBabyChanging":false,"hasAccessible":false,"source":"OpenStreetMap","updatedAt":"2026-06-12T07:40:23.325Z","facilityType":"toilet","facilityLabel":null,"changingTable":false,"wheelchair":false,"needsAddr":true},{"id":635196693,"name":"員山馬偕紀念醫院","lat":24.7213919,"lng":121.7217059,"address":"264宜蘭縣員山鄉尚深路91號","hasBabyChanging":false,"hasAccessible":false,"source":"OpenStreetMap","updatedAt":"2026-06-12T07:40:23.325Z","facilityType":"hospital","facilityLabel":"🏥 醫院","changingTable":false,"wheelchair":false,"needsAddr":false},{"id":675102414,"name":"廟宇","lat":24.7193558,"lng":121.7194705,"address":null,"hasBabyChanging":false,"hasAccessible":false,"source":"OpenStreetMap","updatedAt":"2026-06-12T07:40:23.325Z","facilityType":"temple","facilityLabel":"🛕 廟宇","changingTable":false,"wheelchair":false,"needsAddr":true},{"id":700495284,"name":"員山鄉公所","lat":24.7434461,"lng":121.7231833,"address":null,"hasBabyChanging":false,"hasAccessible":false,"source":"OpenStreetMap","updatedAt":"2026-06-12T07:40:23.325Z","facilityType":"government","facilityLabel":"🏛 公務機關","changingTable":false,"wheelchair":false,"needsAddr":false},{"id":730058886,"name":"員山機堡","lat":24.7462412,"lng":121.7292526,"address":null,"hasBabyChanging":false,"hasAccessible":false,"source":"OpenStreetMap","updatedAt":"2026-06-12T07:40:23.325Z","facilityType":"park","facilityLabel":"🌳 公園","changingTable":false,"wheelchair":false,"needsAddr":false},{"id":823724676,"name":"長嶺苗圃辦公室","lat":24.7070138,"lng":121.6130089,"address":null,"hasBabyChanging":false,"hasAccessible":false,"source":"OpenStreetMap","updatedAt":"2026-06-12T07:40:23.325Z","facilityType":"government","facilityLabel":"🏛 公務機關","changingTable":false,"wheelchair":false,"needsAddr":false},{"id":851425494,"name":"同樂社區活動中心","lat":24.7620837,"lng":121.7296451,"address":"宜蘭縣員山鄉同新路182號","hasBabyChanging":false,"hasAccessible":false,"source":"OpenStreetMap","updatedAt":"2026-06-12T07:40:23.325Z","facilityType":"community","facilityLabel":"🏘️ 活動中心","changingTable":false,"wheelchair":false,"needsAddr":false},{"id":851426653,"name":"結頭份社區活動中心","lat":24.7609759,"lng":121.7202938,"address":"宜蘭縣員山鄉永同路二段186之1號","hasBabyChanging":false,"hasAccessible":false,"source":"OpenStreetMap","updatedAt":"2026-06-12T07:40:23.325Z","facilityType":"community","facilityLabel":"🏘️ 活動中心","changingTable":false,"wheelchair":false,"needsAddr":false},{"id":851441978,"name":"枕山社區活動中心","lat":24.7683348,"lng":121.718352,"address":"宜蘭縣員山鄉枕山路43-1號","hasBabyChanging":false,"hasAccessible":false,"source":"OpenStreetMap","updatedAt":"2026-06-12T07:40:23.325Z","facilityType":"community","facilityLabel":"🏘️ 活動中心","changingTable":false,"wheelchair":false,"needsAddr":false},{"id":851451732,"name":"永和社區活動中心","lat":24.7497052,"lng":121.7103571,"address":"宜蘭縣員山鄉溫泉路62-1號","hasBabyChanging":false,"hasAccessible":false,"source":"OpenStreetMap","updatedAt":"2026-06-12T07:40:23.325Z","facilityType":"community","facilityLabel":"🏘️ 活動中心","changingTable":false,"wheelchair":false,"needsAddr":false},{"id":852229655,"name":"湖東社區活動中心","lat":24.7458272,"lng":121.7072911,"address":null,"hasBabyChanging":false,"hasAccessible":false,"source":"OpenStreetMap","updatedAt":"2026-06-12T07:40:23.325Z","facilityType":"community","facilityLabel":"🏘️ 活動中心","changingTable":false,"wheelchair":false,"needsAddr":false},{"id":852230204,"name":"逸仙社區活動中心","lat":24.7396541,"lng":121.7002181,"address":"宜蘭縣員山鄉大湖十六路181巷2號","hasBabyChanging":false,"hasAccessible":false,"source":"OpenStreetMap","updatedAt":"2026-06-12T07:40:23.325Z","facilityType":"community","facilityLabel":"🏘️ 活動中心","changingTable":false,"wheelchair":false,"needsAddr":false},{"id":852236075,"name":"員山鄉活動中心","lat":24.7452393,"lng":121.7228502,"address":"宜蘭縣員山鄉文化路156號","hasBabyChanging":false,"hasAccessible":false,"source":"OpenStreetMap","updatedAt":"2026-06-12T07:40:23.325Z","facilityType":"community","facilityLabel":"🏘️ 活動中心","changingTable":false,"wheelchair":false,"needsAddr":false},{"id":852239414,"name":"尚德社區活動中心","lat":24.7374256,"lng":121.722516,"address":"宜蘭縣員山鄉三鬮路35巷13號","hasBabyChanging":false,"hasAccessible":false,"source":"OpenStreetMap","updatedAt":"2026-06-12T07:40:23.325Z","facilityType":"community","facilityLabel":"🏘️ 活動中心","changingTable":false,"wheelchair":false,"needsAddr":false},{"id":852244512,"name":"湖北社區活動中心","lat":24.7449652,"lng":121.6976696,"address":"宜蘭縣員山鄉大湖五路50號","hasBabyChanging":false,"hasAccessible":false,"source":"OpenStreetMap","updatedAt":"2026-06-12T07:40:23.325Z","facilityType":"community","facilityLabel":"🏘️ 活動中心","changingTable":false,"wheelchair":false,"needsAddr":false},{"id":852245204,"name":"雙湖社區活動中心","lat":24.7482804,"lng":121.6854624,"address":"宜蘭縣員山鄉隘界路131號","hasBabyChanging":false,"hasAccessible":false,"source":"OpenStreetMap","updatedAt":"2026-06-12T07:40:23.325Z","facilityType":"community","facilityLabel":"🏘️ 活動中心","changingTable":false,"wheelchair":false,"needsAddr":false},{"id":852281257,"name":"惠好社區活動中心","lat":24.7316962,"lng":121.730745,"address":"宜蘭縣員山鄉賢德路二段66巷50號","hasBabyChanging":false,"hasAccessible":false,"source":"OpenStreetMap","updatedAt":"2026-06-12T07:40:23.325Z","facilityType":"community","facilityLabel":"🏘️ 活動中心","changingTable":false,"wheelchair":false,"needsAddr":false},{"id":852302552,"name":"七賢村民眾活動中心","lat":24.7145773,"lng":121.7350763,"address":"宜蘭縣員山鄉賢德路一段61巷25號","hasBabyChanging":false,"hasAccessible":false,"source":"OpenStreetMap","updatedAt":"2026-06-12T07:40:23.325Z","facilityType":"community","facilityLabel":"🏘️ 活動中心","changingTable":false,"wheelchair":false,"needsAddr":false},{"id":852322388,"name":"深溝村集會所","lat":24.7157082,"lng":121.7198422,"address":null,"hasBabyChanging":false,"hasAccessible":false,"source":"OpenStreetMap","updatedAt":"2026-06-12T07:40:23.325Z","facilityType":"community","facilityLabel":"🏘️ 活動中心","changingTable":false,"wheelchair":false,"needsAddr":false},{"id":852328267,"name":"內城社區活動中心","lat":24.7205474,"lng":121.6887398,"address":"宜蘭縣員山鄉榮光路321號","hasBabyChanging":false,"hasAccessible":false,"source":"OpenStreetMap","updatedAt":"2026-06-12T07:40:23.325Z","facilityType":"community","facilityLabel":"🏘️ 活動中心","changingTable":false,"wheelchair":false,"needsAddr":false},{"id":852334261,"name":"蓁巷社區活動中心","lat":24.713556,"lng":121.6956277,"address":"宜蘭縣員山鄉成功路45號","hasBabyChanging":false,"hasAccessible":false,"source":"OpenStreetMap","updatedAt":"2026-06-12T07:40:23.325Z","facilityType":"community","facilityLabel":"🏘️ 活動中心","changingTable":false,"wheelchair":false,"needsAddr":false},{"id":852575147,"name":"中華村集會所","lat":24.7093534,"lng":121.6466733,"address":"宜蘭縣員山鄉粗坑路304號","hasBabyChanging":false,"hasAccessible":false,"source":"OpenStreetMap","updatedAt":"2026-06-12T07:40:23.325Z","facilityType":"community","facilityLabel":"🏘️ 活動中心","changingTable":false,"wheelchair":false,"needsAddr":false},{"id":1074509577,"name":"北后寺","lat":24.7264332,"lng":121.7089935,"address":"宜蘭縣員山鄉八甲路4號","hasBabyChanging":false,"hasAccessible":false,"source":"OpenStreetMap","updatedAt":"2026-06-12T07:40:23.325Z","facilityType":"temple","facilityLabel":"🛕 廟宇","changingTable":false,"wheelchair":false,"needsAddr":false},{"id":1113286765,"name":"豬龍寨 波的波可窯烤披薩","lat":24.7739848,"lng":121.6992737,"address":null,"hasBabyChanging":false,"hasAccessible":false,"source":"OpenStreetMap","updatedAt":"2026-06-12T07:40:23.325Z","facilityType":"toilet","facilityLabel":null,"changingTable":false,"wheelchair":false,"needsAddr":false},{"id":1113286766,"name":"公共廁所","lat":24.7740033,"lng":121.6987237,"address":null,"hasBabyChanging":false,"hasAccessible":false,"source":"OpenStreetMap","updatedAt":"2026-06-12T07:40:23.325Z","facilityType":"toilet","facilityLabel":null,"changingTable":false,"wheelchair":false,"needsAddr":true},{"id":1115896529,"name":"三興廟","lat":24.7090016,"lng":121.7169915,"address":null,"hasBabyChanging":false,"hasAccessible":false,"source":"OpenStreetMap","updatedAt":"2026-06-12T07:40:23.325Z","facilityType":"temple","facilityLabel":"🛕 廟宇","changingTable":false,"wheelchair":false,"needsAddr":false},{"id":1115896530,"name":"員山廣興堂","lat":24.7080072,"lng":121.7222411,"address":null,"hasBabyChanging":false,"hasAccessible":false,"source":"OpenStreetMap","updatedAt":"2026-06-12T07:40:23.325Z","facilityType":"temple","facilityLabel":"🛕 廟宇","changingTable":false,"wheelchair":false,"needsAddr":false},{"id":1116730223,"name":"勝洋休閒農場","lat":24.7281673,"lng":121.7047499,"address":null,"hasBabyChanging":false,"hasAccessible":false,"source":"OpenStreetMap","updatedAt":"2026-06-12T07:40:23.325Z","facilityType":"attraction","facilityLabel":"🏞️ 景點","changingTable":false,"wheelchair":false,"needsAddr":false},{"id":1116730240,"name":"普照寺","lat":24.7200251,"lng":121.6896109,"address":null,"hasBabyChanging":false,"hasAccessible":false,"source":"OpenStreetMap","updatedAt":"2026-06-12T07:40:23.325Z","facilityType":"temple","facilityLabel":"🛕 廟宇","changingTable":false,"wheelchair":false,"needsAddr":false},{"id":1116731689,"name":"千慧寺","lat":24.7236334,"lng":121.6789759,"address":null,"hasBabyChanging":false,"hasAccessible":false,"source":"OpenStreetMap","updatedAt":"2026-06-12T07:40:23.325Z","facilityType":"temple","facilityLabel":"🛕 廟宇","changingTable":false,"wheelchair":false,"needsAddr":false},{"id":1195063153,"name":"慶安廟","lat":24.7684798,"lng":121.7186871,"address":null,"hasBabyChanging":false,"hasAccessible":false,"source":"OpenStreetMap","updatedAt":"2026-06-12T07:40:23.325Z","facilityType":"temple","facilityLabel":"🛕 廟宇","changingTable":false,"wheelchair":false,"needsAddr":false},{"id":1196013106,"name":"永廣廟","lat":24.7593682,"lng":121.7138379,"address":null,"hasBabyChanging":false,"hasAccessible":false,"source":"OpenStreetMap","updatedAt":"2026-06-12T07:40:23.325Z","facilityType":"temple","facilityLabel":"🛕 廟宇","changingTable":false,"wheelchair":false,"needsAddr":false},{"id":1196017766,"name":"讚化宮","lat":24.7608126,"lng":121.7203064,"address":null,"hasBabyChanging":false,"hasAccessible":false,"source":"OpenStreetMap","updatedAt":"2026-06-12T07:40:23.325Z","facilityType":"temple","facilityLabel":"🛕 廟宇","changingTable":false,"wheelchair":false,"needsAddr":false},{"id":1197284442,"name":"湖北社區活動中心","lat":24.7435073,"lng":121.6983869,"address":null,"hasBabyChanging":false,"hasAccessible":false,"source":"OpenStreetMap","updatedAt":"2026-06-12T07:40:23.325Z","facilityType":"community","facilityLabel":"🏘️ 活動中心","changingTable":false,"wheelchair":false,"needsAddr":false},{"id":1386356767,"name":"久天宮九天道場","lat":24.7793511,"lng":121.6965903,"address":null,"hasBabyChanging":false,"hasAccessible":false,"source":"OpenStreetMap","updatedAt":"2026-06-12T07:40:23.325Z","facilityType":"temple","facilityLabel":"🛕 廟宇","changingTable":false,"wheelchair":false,"needsAddr":false},{"id":1387116531,"name":"再連福德廟","lat":24.712034,"lng":121.6668151,"address":null,"hasBabyChanging":false,"hasAccessible":false,"source":"OpenStreetMap","updatedAt":"2026-06-12T07:40:23.325Z","facilityType":"temple","facilityLabel":"🛕 廟宇","changingTable":false,"wheelchair":false,"needsAddr":false},{"id":1408942408,"name":"員山鄉圖書館","lat":24.7451229,"lng":121.7226756,"address":null,"hasBabyChanging":false,"hasAccessible":false,"source":"OpenStreetMap","updatedAt":"2026-06-12T07:40:23.325Z","facilityType":"library","facilityLabel":"📚 圖書館","changingTable":false,"wheelchair":false,"needsAddr":false},{"id":1484854615,"name":"枕山慈德宮","lat":24.7710643,"lng":121.7217957,"address":null,"hasBabyChanging":false,"hasAccessible":false,"source":"OpenStreetMap","updatedAt":"2026-06-12T07:40:23.325Z","facilityType":"temple","facilityLabel":"🛕 廟宇","changingTable":false,"wheelchair":false,"needsAddr":false},{"id":7945147,"name":"台北榮總員山分院","lat":24.7224998,"lng":121.6878461,"address":"264宜蘭縣員山鄉榮光路386號","hasBabyChanging":false,"hasAccessible":false,"source":"OpenStreetMap","updatedAt":"2026-06-12T07:40:23.325Z","facilityType":"hospital","facilityLabel":"🏥 醫院","changingTable":false,"wheelchair":false,"needsAddr":false}]}