{"city":"苗栗縣","district":"頭份市","category":"family","updatedAt":"2026-06-16T15:54:24.202Z","rev":24,"count":27,"items":[{"id":3480404729,"name":"楓香林","lat":24.6874525,"lng":120.9471968,"address":null,"hasBabyChanging":false,"hasAccessible":false,"source":"OpenStreetMap","updatedAt":"2026-06-16T15:54:24.202Z","facilityType":"tourist_attraction","facilityLabel":"🧭 旅遊景點","phone":null,"website":null,"wheelchair":false,"paid":null,"needsAddr":true},{"id":7402398337,"name":"頭份後花園步道楓林吊橋入口","lat":24.6910852,"lng":120.9503264,"address":null,"hasBabyChanging":false,"hasAccessible":false,"source":"OpenStreetMap","updatedAt":"2026-06-16T15:54:24.202Z","facilityType":"tourist_attraction","facilityLabel":"🧭 旅遊景點","phone":null,"website":null,"wheelchair":false,"paid":null,"needsAddr":true},{"id":7402487009,"name":"景觀棧道","lat":24.6923566,"lng":120.9556066,"address":null,"hasBabyChanging":false,"hasAccessible":false,"source":"OpenStreetMap","updatedAt":"2026-06-16T15:54:24.202Z","facilityType":"tourist_attraction","facilityLabel":"🧭 旅遊景點","phone":null,"website":null,"wheelchair":false,"paid":null,"needsAddr":true},{"id":7402487014,"name":"觀景平台","lat":24.6941,"lng":120.9483357,"address":null,"hasBabyChanging":false,"hasAccessible":false,"source":"OpenStreetMap","updatedAt":"2026-06-16T15:54:24.202Z","facilityType":"tourist_attraction","facilityLabel":"🧭 旅遊景點","phone":null,"website":null,"wheelchair":false,"paid":null,"needsAddr":true},{"id":7402487015,"name":"樹屋平台","lat":24.6947353,"lng":120.948035,"address":null,"hasBabyChanging":false,"hasAccessible":false,"source":"OpenStreetMap","updatedAt":"2026-06-16T15:54:24.202Z","facilityType":"tourist_attraction","facilityLabel":"🧭 旅遊景點","phone":null,"website":null,"wheelchair":false,"paid":null,"needsAddr":true},{"id":8289269317,"name":"蘆竹湳古厝","lat":24.6770549,"lng":120.8899215,"address":null,"hasBabyChanging":false,"hasAccessible":false,"source":"OpenStreetMap","updatedAt":"2026-06-16T15:54:24.202Z","facilityType":"tourist_attraction","facilityLabel":"🧭 旅遊景點","phone":null,"website":null,"wheelchair":false,"paid":null,"needsAddr":true},{"id":8780139217,"name":"楓林步道","lat":24.68753,"lng":120.9464129,"address":null,"hasBabyChanging":false,"hasAccessible":false,"source":"OpenStreetMap","updatedAt":"2026-06-16T15:54:24.202Z","facilityType":"tourist_attraction","facilityLabel":"🧭 旅遊景點","phone":null,"website":null,"wheelchair":false,"paid":null,"needsAddr":true},{"id":10718199509,"name":"林家祖厝藝文館","lat":24.6763847,"lng":120.8895485,"address":null,"hasBabyChanging":false,"hasAccessible":false,"source":"OpenStreetMap","updatedAt":"2026-06-16T15:54:24.202Z","facilityType":"tourist_attraction","facilityLabel":"🧭 旅遊景點","phone":null,"website":null,"wheelchair":false,"paid":null,"needsAddr":true},{"id":198874030,"name":"下公園","lat":24.6838774,"lng":120.9061571,"address":null,"hasBabyChanging":false,"hasAccessible":false,"source":"OpenStreetMap","updatedAt":"2026-06-16T15:54:24.202Z","facilityType":"park","facilityLabel":"🌳 小型公園","phone":null,"website":null,"wheelchair":false,"paid":null,"needsAddr":true},{"id":198874038,"name":"上公園","lat":24.6871364,"lng":120.91084989999999,"address":null,"hasBabyChanging":false,"hasAccessible":false,"source":"OpenStreetMap","updatedAt":"2026-06-16T15:54:24.202Z","facilityType":"park","facilityLabel":"🌳 小型公園","phone":null,"website":null,"wheelchair":false,"paid":null,"needsAddr":true},{"id":198876061,"name":"蟠桃公園","lat":24.696469,"lng":120.9112518,"address":null,"hasBabyChanging":false,"hasAccessible":false,"source":"OpenStreetMap","updatedAt":"2026-06-16T15:54:24.202Z","facilityType":"park","facilityLabel":"🌳 中型公園","phone":null,"website":null,"wheelchair":false,"paid":null,"needsAddr":true},{"id":265600398,"name":"竹南運動公園","lat":24.689027099999997,"lng":120.88879265,"address":null,"hasBabyChanging":false,"hasAccessible":false,"source":"OpenStreetMap","updatedAt":"2026-06-16T15:54:24.202Z","facilityType":"park","facilityLabel":"🌳 大型公園","phone":null,"website":null,"wheelchair":false,"paid":null,"needsAddr":true},{"id":314683343,"name":"維也納公園","lat":24.64745945,"lng":120.88920064999999,"address":null,"hasBabyChanging":false,"hasAccessible":false,"source":"OpenStreetMap","updatedAt":"2026-06-16T15:54:24.202Z","facilityType":"park","facilityLabel":"🌳 中型公園","phone":null,"website":null,"wheelchair":false,"paid":null,"needsAddr":true},{"id":340788419,"name":"楓林吊橋","lat":24.691154,"lng":120.9502856,"address":null,"hasBabyChanging":false,"hasAccessible":false,"source":"OpenStreetMap","updatedAt":"2026-06-16T15:54:24.202Z","facilityType":"tourist_attraction","facilityLabel":"🧭 旅遊景點","phone":null,"website":null,"wheelchair":false,"paid":null,"needsAddr":true},{"id":397963892,"name":"東興橋人工溼地","lat":24.67174855,"lng":120.8955601,"address":null,"hasBabyChanging":false,"hasAccessible":false,"source":"OpenStreetMap","updatedAt":"2026-06-16T15:54:24.202Z","facilityType":"park","facilityLabel":"🌳 中型公園","phone":null,"website":"http://ecological.epa.gov.tw/Engineering.aspx?num1=33&num2=1","wheelchair":false,"paid":null,"needsAddr":true},{"id":472996144,"name":"頭份運動公園","lat":24.68963175,"lng":120.89147135,"address":null,"hasBabyChanging":false,"hasAccessible":false,"source":"OpenStreetMap","updatedAt":"2026-06-16T15:54:24.202Z","facilityType":"park","facilityLabel":"🌳 中型公園","phone":null,"website":null,"wheelchair":false,"paid":null,"needsAddr":true},{"id":544951096,"name":"大埔七街小公園","lat":24.70428135,"lng":120.89846265,"address":null,"hasBabyChanging":false,"hasAccessible":false,"source":"OpenStreetMap","updatedAt":"2026-06-16T15:54:24.202Z","facilityType":"park","facilityLabel":"🌳 小型公園","phone":null,"website":null,"wheelchair":false,"paid":null,"needsAddr":true},{"id":698485922,"name":"陶藝館","lat":24.68417685,"lng":120.9689903,"address":null,"hasBabyChanging":false,"hasAccessible":false,"source":"OpenStreetMap","updatedAt":"2026-06-16T15:54:24.202Z","facilityType":"diy","facilityLabel":"🧶 DIY手作","phone":null,"website":null,"wheelchair":false,"paid":null,"needsAddr":true},{"id":988794671,"name":"大亨公園","lat":24.69498425,"lng":120.90415465000001,"address":null,"hasBabyChanging":false,"hasAccessible":false,"source":"OpenStreetMap","updatedAt":"2026-06-16T15:54:24.202Z","facilityType":"park","facilityLabel":"🌳 小型公園","phone":null,"website":null,"wheelchair":false,"paid":null,"needsAddr":true},{"id":988794672,"name":"德義兒童公園","lat":24.69092675,"lng":120.8971281,"address":null,"hasBabyChanging":false,"hasAccessible":false,"source":"OpenStreetMap","updatedAt":"2026-06-16T15:54:24.202Z","facilityType":"park","facilityLabel":"🌳 小型公園","phone":null,"website":null,"wheelchair":false,"paid":null,"needsAddr":true},{"id":988794674,"name":"藝術公園","lat":24.688204,"lng":120.89998445,"address":null,"hasBabyChanging":false,"hasAccessible":false,"source":"OpenStreetMap","updatedAt":"2026-06-16T15:54:24.202Z","facilityType":"park","facilityLabel":"🌳 小型公園","phone":null,"website":null,"wheelchair":false,"paid":null,"needsAddr":true},{"id":988794675,"name":"音樂公園","lat":24.687270650000002,"lng":120.90018475,"address":null,"hasBabyChanging":false,"hasAccessible":false,"source":"OpenStreetMap","updatedAt":"2026-06-16T15:54:24.202Z","facilityType":"park","facilityLabel":"🌳 小型公園","phone":null,"website":null,"wheelchair":false,"paid":null,"needsAddr":true},{"id":988794676,"name":"童話公園","lat":24.688366549999998,"lng":120.8956486,"address":null,"hasBabyChanging":false,"hasAccessible":false,"source":"OpenStreetMap","updatedAt":"2026-06-16T15:54:24.202Z","facilityType":"park","facilityLabel":"🌳 小型公園","phone":null,"website":null,"wheelchair":false,"paid":null,"needsAddr":true},{"id":988794679,"name":"忠孝公園","lat":24.693260199999997,"lng":120.909067,"address":null,"hasBabyChanging":false,"hasAccessible":false,"source":"OpenStreetMap","updatedAt":"2026-06-16T15:54:24.202Z","facilityType":"park","facilityLabel":"🌳 小型公園","phone":null,"website":null,"wheelchair":false,"paid":null,"needsAddr":true},{"id":1075759815,"name":"滿燭DIY蠟燭故事館","lat":24.6730182,"lng":120.89096765,"address":null,"hasBabyChanging":false,"hasAccessible":false,"source":"OpenStreetMap","updatedAt":"2026-06-16T15:54:24.202Z","facilityType":"diy","facilityLabel":"🧶 DIY手作","phone":null,"website":null,"wheelchair":false,"paid":null,"needsAddr":true},{"id":1167354252,"name":"大埤塘公園","lat":24.67512385,"lng":120.92431895,"address":null,"hasBabyChanging":false,"hasAccessible":false,"source":"OpenStreetMap","updatedAt":"2026-06-16T15:54:24.202Z","facilityType":"park","facilityLabel":"🌳 小型公園","phone":null,"website":null,"wheelchair":false,"paid":null,"needsAddr":true},{"id":1297673180,"name":"威武長青公園","lat":24.6753364,"lng":120.9448606,"address":null,"hasBabyChanging":false,"hasAccessible":false,"source":"OpenStreetMap","updatedAt":"2026-06-16T15:54:24.202Z","facilityType":"park","facilityLabel":"🌳 小型公園","phone":null,"website":null,"wheelchair":false,"paid":null,"needsAddr":true}]}