{
  "city": "新竹縣",
  "category": "family",
  "updatedAt": "2026-06-12T20:33:12.884Z",
  "items": [
    {
      "id": 5441902621,
      "name": "鄒洪將軍故居",
      "facilityType": "culture",
      "facilityLabel": "🎨 藝文場館",
      "lat": 24.7451881,
      "lng": 121.1450414,
      "source": "OpenStreetMap",
      "updatedAt": "2026-06-12T20:33:12.875Z"
    },
    {
      "id": 9442246882,
      "name": "觀景點",
      "facilityType": "tourist_attraction",
      "facilityLabel": "🧭 旅遊景點",
      "lat": 24.7920657,
      "lng": 121.1079745,
      "source": "OpenStreetMap",
      "updatedAt": "2026-06-12T20:33:12.877Z"
    },
    {
      "id": 10607442374,
      "name": "劉家果園觀景平台",
      "facilityType": "tourist_attraction",
      "facilityLabel": "🧭 旅遊景點",
      "lat": 24.8000454,
      "lng": 121.0751673,
      "source": "OpenStreetMap",
      "updatedAt": "2026-06-12T20:33:12.877Z"
    },
    {
      "id": 10657208638,
      "name": "石桌平台",
      "facilityType": "tourist_attraction",
      "facilityLabel": "🧭 旅遊景點",
      "lat": 24.7526809,
      "lng": 121.1346879,
      "source": "OpenStreetMap",
      "updatedAt": "2026-06-12T20:33:12.878Z"
    },
    {
      "id": 10657208639,
      "name": "十胞胎",
      "facilityType": "tourist_attraction",
      "facilityLabel": "🧭 旅遊景點",
      "lat": 24.7548853,
      "lng": 121.135625,
      "source": "OpenStreetMap",
      "updatedAt": "2026-06-12T20:33:12.879Z"
    },
    {
      "id": 10666312585,
      "name": "七兄弟樹",
      "facilityType": "tourist_attraction",
      "facilityLabel": "🧭 旅遊景點",
      "lat": 24.7929422,
      "lng": 121.1063392,
      "source": "OpenStreetMap",
      "updatedAt": "2026-06-12T20:33:12.880Z"
    },
    {
      "id": 10698690021,
      "name": "紙寮窩山情人座",
      "facilityType": "tourist_attraction",
      "facilityLabel": "🧭 旅遊景點",
      "lat": 24.7831005,
      "lng": 121.0862211,
      "source": "OpenStreetMap",
      "updatedAt": "2026-06-12T20:33:12.880Z"
    },
    {
      "id": 10767840744,
      "name": "新竹",
      "facilityType": "visitor_center",
      "facilityLabel": "🛎 旅客中心",
      "lat": 24.7709262,
      "lng": 121.0849227,
      "source": "OpenStreetMap",
      "updatedAt": "2026-06-12T20:33:12.881Z"
    },
    {
      "id": 10789655905,
      "name": "血藤花",
      "facilityType": "tourist_attraction",
      "facilityLabel": "🧭 旅遊景點",
      "lat": 24.7548918,
      "lng": 121.1060651,
      "source": "OpenStreetMap",
      "updatedAt": "2026-06-12T20:33:12.882Z"
    },
    {
      "id": 10815487805,
      "name": "血藤花",
      "facilityType": "tourist_attraction",
      "facilityLabel": "🧭 旅遊景點",
      "lat": 24.7545702,
      "lng": 121.1055763,
      "source": "OpenStreetMap",
      "updatedAt": "2026-06-12T20:33:12.882Z"
    },
    {
      "id": 11917129164,
      "name": "小森之歌",
      "facilityType": "tourist_attraction",
      "facilityLabel": "🧭 旅遊景點",
      "lat": 24.7704162,
      "lng": 121.1056895,
      "source": "OpenStreetMap",
      "updatedAt": "2026-06-12T20:33:12.884Z"
    }
  ]
}
